scrape_nhs_conditions/__init__.py
scrape_nhs_conditions/data_exports/__init__.py
scrape_nhs_conditions/data_ingestion/__init__.py
scrape_nhs_conditions/data_ingestion/simple_nhs_conditions_scrape.py
scrape_nhs_conditions/processing/__init__.py
scrape_nhs_conditions/processing/process_html.py
scrape_nhs_conditions/utils/__init__.py
scrape_nhs_conditions-1.0.4.dist-info/LICENCE
scrape_nhs_conditions-1.0.4.dist-info/METADATA
scrape_nhs_conditions-1.0.4.dist-info/WHEEL
scrape_nhs_conditions-1.0.4.dist-info/top_level.txt
scrape_nhs_conditions-1.0.4.dist-info/RECORD
