Metadata-Version: 2.1
Name: scrape_nhs_conditions
Version: 1.0.4
Author-email: Data Science team <datascience@nhs.net>
Project-URL: Homepage, https://github.com/nhsengland/scrape_nhs_conditions
Classifier: Programming Language :: Python :: 3
Classifier: License :: OSI Approved :: MIT License
Classifier: Operating System :: OS Independent
Requires-Python: >=3.10
License-File: LICENCE
Requires-Dist: toml
Requires-Dist: dateutils
Requires-Dist: scrapy
Requires-Dist: jupyter
Requires-Dist: jsonlines
Requires-Dist: python-dotenv
Requires-Dist: black
Requires-Dist: black[jupyter]
Requires-Dist: pytest
Requires-Dist: isort
